Metadata-Version: 2.1
Name: facialfinder
Version: 0.0.5
Summary: Simple tool for Face Detection on Image or Video, realtime detection support.
Home-page: https://github.com/Anonimous05/FacialFinder
Author: Airas Tolonov
Author-email: airastolonov05@gmail.com
License-File: LICENSE.txt
Requires-Dist: numpy==1.26.4
Requires-Dist: opencv-python==4.9.0.80
Requires-Dist: progressbar2==4.4.2
